algo_trading/__init__.py
algo_trading/classes/__init__.py
algo_trading/classes/classes.py
algo_trading/classes/core.py
algo_trading/classes/functions.py
algo_trading/classes/info.py
algo_trading/functions/__init__.py
algo_trading/functions/research_tools.py
algotrading_api-0.0.1.dist-info/METADATA
algotrading_api-0.0.1.dist-info/RECORD
algotrading_api-0.0.1.dist-info/WHEEL
algotrading_api-0.0.1.dist-info/top_level.txt
