Metadata-Version: 2.1
Name: algotrading-api
Version: 0.0.1
Summary: A package to test trading algorithms.
Home-page: https://github.com/jdry1729/algo-trading
Author: Jack Dry
Author-email: jack_dry@outlook.com
License: UNKNOWN
Platform: UNKNOWN
Classifier: Programming Language :: Python :: 3
Classifier: Operating System :: OS Independent
Requires-Dist: matplotlib
Requires-Dist: pandas
Requires-Dist: termcolor
Requires-Dist: numpy
Requires-Dist: statsmodels
